_internal/__init__.py
_internal/_config.py
_internal/_core_metadata.py
_internal/_core_utils.py
_internal/_dataclasses.py
_internal/_decorators.py
_internal/_decorators_v1.py
_internal/_discriminated_union.py
_internal/_docs_extraction.py
_internal/_fields.py
_internal/_forward_ref.py
_internal/_generate_schema.py
_internal/_generics.py
_internal/_git.py
_internal/_internal_dataclass.py
_internal/_known_annotated_metadata.py
_internal/_mock_val_ser.py
_internal/_model_construction.py
_internal/_repr.py
_internal/_schema_generation_shared.py
_internal/_signature.py
_internal/_std_types_schema.py
_internal/_typing_extra.py
_internal/_utils.py
_internal/_validate_call.py
_internal/_validators.py
client/realsense.py
embodied-agents/docs/generate_api_docs.py
embodied-agents/examples/1_simple_robot_agent.py
embodied-agents/examples/2_openvla_motor_agent_example.py
embodied-agents/examples/3_reason_plan_act_robot.py
embodied-agents/examples/4_language_reason_plan_act_robot.py
embodied-agents/examples/5_teach_robot_record_dataset.py
embodied-agents/examples/servers/gradio_example_openvla.py
embodied-agents/mbodied/__about__.py
embodied-agents/mbodied/__init__.py
embodied-agents/mbodied/agents/__init__.py
embodied-agents/mbodied/agents/agent.py
embodied-agents/mbodied/agents/cli.py
embodied-agents/mbodied/agents/auto/__init__.py
embodied-agents/mbodied/agents/auto/auto_agent.py
embodied-agents/mbodied/agents/backends/__init__.py
embodied-agents/mbodied/agents/backends/anthropic_backend.py
embodied-agents/mbodied/agents/backends/backend.py
embodied-agents/mbodied/agents/backends/gradio_backend.py
embodied-agents/mbodied/agents/backends/httpx_backend.py
embodied-agents/mbodied/agents/backends/ollama_backend.py
embodied-agents/mbodied/agents/backends/openai_backend.py
embodied-agents/mbodied/agents/backends/serializer.py
embodied-agents/mbodied/agents/backends/vision2seq_backend.py
embodied-agents/mbodied/agents/language/__init__.py
synaptic-0.0.7.dist-info/LICENSE
synaptic-0.0.7.dist-info/METADATA
synaptic-0.0.7.dist-info/WHEEL
synaptic-0.0.7.dist-info/entry_points.txt
synaptic-0.0.7.dist-info/top_level.txt
synaptic-0.0.7.dist-info/RECORD
