Metadata-Version: 2.1
Name: synaptic
Version: 0.0.7
Author: mbodiai
Project-URL: Documentation, https://github.com/mbodiai/synaptic#readme
Project-URL: Issues, https://github.com/mbodiai/synaptic/issues
Project-URL: Source, https://github.com/mbodiai/synaptic
Classifier: Development Status :: 4 - Beta
Classifier: Programming Language :: Python
Classifier: Programming Language :: Python :: 3.10
Classifier: Programming Language :: Python :: 3.11
Classifier: Programming Language :: Python :: 3.12
Classifier: Programming Language :: Python :: Implementation :: CPython
Classifier: Programming Language :: Python :: Implementation :: PyPy
Requires-Python: >=3.10
License-File: LICENSE
Requires-Dist: eclipse-zenoh>=0.11.0
Requires-Dist: fastapi>=0.115.0
Requires-Dist: mbodied>=1.2.1
Requires-Dist: mbpy>=1.0.1
Requires-Dist: more-itertools>=10.5.0
Requires-Dist: msgpack>=1.0.2
Requires-Dist: numpy==1.26.4
Requires-Dist: pydantic-settings>=2.5.2
Requires-Dist: pytest>=8.3.3
Requires-Dist: requests>=2.32.3
Requires-Dist: uvicorn>=0.30.6
Requires-Dist: websockets>=10.0
